aoupy/__init__.py
aoupy/bucket.py
aoupy/misc.py
aoupy-0.0.2.dist-info/METADATA
aoupy-0.0.2.dist-info/WHEEL
aoupy-0.0.2.dist-info/licenses/LICENSE
aoupy-0.0.2.dist-info/RECORD
