Metadata-Version: 2.3
Name: aoupy
Version: 0.0.2
Summary: A toolkit to work with All of Us data.
Author-email: Adnan Cihan Cakar <cakar.adnancihan@gmail.com>
Maintainer-email: Adnan Cihan Cakar <cakar.adnancihan@gmail.com>
License-File: LICENSE
Keywords: allofus,bioinformatics
Classifier: Development Status :: 5 - Production/Stable
Classifier: Programming Language :: Python
Requires-Python: >=3.9
Requires-Dist: polars
